{"acc_base_task_1": 38.1, "acc_ema_task_1": 10.1, "acc_base_task_2": 0.0, "acc_ema_task_2": 0.0, "acc_base_task_3": 0.0, "acc_ema_task_3": 0.0, "acc_base_task_4": 0.0, "acc_ema_task_4": 0.0, "acc_base_task_5": 0.0, "acc_ema_task_5": 0.0, "acc_base_task_6": 0.0, "acc_ema_task_6": 0.0, "acc_base_task_7": 0.0, "acc_ema_task_7": 0.0, "acc_base_task_8": 0.0, "acc_ema_task_8": 0.0, "acc_base_task_9": 0.0, "acc_ema_task_9": 0.0, "acc_base_task_10": 0.0, "acc_ema_task_10": 0.0, "_runtime": 124, "_timestamp": 1638268906, "_step": 0}